yaml2plot/__init__.py
yaml2plot/cli.py
yaml2plot/loader.py
yaml2plot/py.typed
yaml2plot/core/__init__.py
yaml2plot/core/plotspec.py
yaml2plot/core/plotting.py
yaml2plot/core/wavedataset.py
yaml2plot/utils/__init__.py
yaml2plot/utils/env.py
yaml2plot-2.0.1.dist-info/licenses/LICENSE
yaml2plot-2.0.1.dist-info/METADATA
yaml2plot-2.0.1.dist-info/WHEEL
yaml2plot-2.0.1.dist-info/entry_points.txt
yaml2plot-2.0.1.dist-info/top_level.txt
yaml2plot-2.0.1.dist-info/RECORD
